nexpy/__init__.py
nexpy/_version.py
nexpy/nexpygui.py
nexpy/examples/README.rst
nexpy/examples/chopper.nxs
nexpy/examples/example.nxs
nexpy/examples/plugins/README.rst
nexpy/examples/plugins/chopper_plugin/pyproject.toml
nexpy/examples/plugins/chopper_plugin/chopper/__init__.py
nexpy/examples/plugins/chopper_plugin/chopper/__init__.pyc
nexpy/examples/plugins/chopper_plugin/chopper/convert_qe.py
nexpy/examples/plugins/chopper_plugin/chopper/convert_qe.pyc
nexpy/examples/plugins/chopper_plugin/chopper/get_ei.py
nexpy/examples/plugins/chopper_plugin/chopper/get_ei.pyc
nexpy/examples/scripts/README.rst
nexpy/examples/scripts/chopper_plot.py
nexpy/examples/scripts/example.py
nexpy/gui/__init__.py
nexpy/gui/consoleapp.py
nexpy/gui/datadialogs.py
nexpy/gui/dialogs.py
nexpy/gui/fitdialogs.py
nexpy/gui/importdialog.py
nexpy/gui/mainwindow.py
nexpy/gui/plotview.py
nexpy/gui/pyqt.py
nexpy/gui/scripteditor.py
nexpy/gui/treeview.py
nexpy/gui/utils.py
nexpy/gui/widgets.py
nexpy/gui/resources/NeXpy.png
nexpy/gui/resources/NeXpy.svg
nexpy/gui/resources/back.png
nexpy/gui/resources/backward-icon.png
nexpy/gui/resources/customize.png
nexpy/gui/resources/equal.png
nexpy/gui/resources/export-data.png
nexpy/gui/resources/export-figure.png
nexpy/gui/resources/filesave.png
nexpy/gui/resources/forward-icon.png
nexpy/gui/resources/forward.png
nexpy/gui/resources/hand.png
nexpy/gui/resources/home.png
nexpy/gui/resources/link-icon.png
nexpy/gui/resources/lock-icon.png
nexpy/gui/resources/lock-red-icon.png
nexpy/gui/resources/modify-style.png
nexpy/gui/resources/move.png
nexpy/gui/resources/pause-icon.png
nexpy/gui/resources/refresh-icon.png
nexpy/gui/resources/unlock-icon.png
nexpy/gui/resources/unlock-red-icon.png
nexpy/gui/resources/zoom_to_rect.png
nexpy/models/bose.py
nexpy/models/critexp.py
nexpy/models/op.py
nexpy/models/pdfdecay.py
nexpy/readers/readnpy.py
nexpy/readers/readspec.py
nexpy/readers/readstack.py
nexpy/readers/readtiff.py
nexpy/readers/readtxt.py
nexpy-2.0.0.dist-info/licenses/COPYING
nexpy-2.0.0.dist-info/METADATA
nexpy-2.0.0.dist-info/WHEEL
nexpy-2.0.0.dist-info/entry_points.txt
nexpy-2.0.0.dist-info/pbr.json
nexpy-2.0.0.dist-info/top_level.txt
nexpy-2.0.0.dist-info/RECORD
