Metadata-Version: 2.4
Name: NeXpy
Version: 2.0.0
Summary: Python GUI to analyze NeXus data
Author-email: Raymond Osborn <rayosborn@mac.com>
License: Licensing Terms for NeXpy
Project-URL: Homepage, https://nexpy.github.io/nexpy
Project-URL: Repository, https://github.com/nexpy/nexpy.git
Project-URL: Issues, https://github.com/nexpy/nexpy/issues
Project-URL: Documentation, https://nexpy.github.io/nexpy
Project-URL: Changelog, https://github.com/nexpy/nexpy/releases
Keywords: neutron scattering,x-ray scattering,data analysis,visualization
Classifier: Development Status :: 5 - Production/Stable
Classifier: License :: OSI Approved :: BSD License
Classifier: Intended Audience :: Developers
Classifier: Intended Audience :: Science/Research
Classifier: Topic :: Scientific/Engineering
Classifier: Programming Language :: Python :: 3
Classifier: Programming Language :: Python :: 3.9
Classifier: Programming Language :: Python :: 3.10
Classifier: Programming Language :: Python :: 3.11
Classifier: Programming Language :: Python :: 3.12
Classifier: Programming Language :: Python :: 3.13
Classifier: Topic :: Scientific/Engineering
Classifier: Topic :: Scientific/Engineering :: Visualization
Requires-Python: >=3.9
License-File: COPYING
Requires-Dist: ansi2html
Requires-Dist: fabio
Requires-Dist: h5py
Requires-Dist: ipython
Requires-Dist: lmfit
Requires-Dist: matplotlib
Requires-Dist: mplcursors
Requires-Dist: nexusformat>=2.0.0
Requires-Dist: numpy
Requires-Dist: packaging
Requires-Dist: pillow
Requires-Dist: pygments
Requires-Dist: pylatexenc
Requires-Dist: qtconsole
Requires-Dist: qtpy
Requires-Dist: scipy
Requires-Dist: importlib_metadata; python_version < "3.10"
Requires-Dist: importlib_resources; python_version < "3.10"
Provides-Extra: testing
Requires-Dist: pytest; extra == "testing"
Provides-Extra: spec
Requires-Dist: spec2nexus; extra == "spec"
Dynamic: license-file
